prettimer/__init__.py
prettimer/logutils.py
prettimer-0.0.2.dist-info/LICENSE
prettimer-0.0.2.dist-info/METADATA
prettimer-0.0.2.dist-info/WHEEL
prettimer-0.0.2.dist-info/top_level.txt
prettimer-0.0.2.dist-info/RECORD
