Metadata-Version: 2.1
Name: prettimer
Version: 0.0.2
Summary: UNKNOWN
Home-page: https://gitlab.com/giordano.zanoli/prettimer
Author: Giordano Zanoli
Author-email: giordano.zanoli84@gmail.com
License: UNKNOWN
Platform: UNKNOWN
Classifier: Programming Language :: Python :: 3
Classifier: License :: OSI Approved :: MIT License
Classifier: Topic :: Software Development :: Libraries :: Python Modules
Provides-Extra: dev
Requires-Dist: pytest (==5.0.1) ; extra == 'dev'
Requires-Dist: Sphinx (==1.8.2) ; extra == 'dev'
Requires-Dist: sphinx-rtd-theme (==0.4.2) ; extra == 'dev'
Requires-Dist: numpydoc (==0.8.0) ; extra == 'dev'
Requires-Dist: check-manifest (==0.39) ; extra == 'dev'
Requires-Dist: twine (==1.13) ; extra == 'dev'
